[{"id":1,"name":"Laurice","email":"lmouan0@bing.com","gender":"Polygender", "image":"https://i.ibb.co/nwcKWrT/ajay.jpg", "salary":100},
{"id":2,"name":"Gelya","email":"ggalea1@scientificamerican.com","gender":"Non-binary", "image":"https://i.ibb.co/SngP7nh/a.jpg", "salary":1200},
{"id":3,"name":"Janis","email":"jgallico2@usnews.com","gender":"Genderfluid", "image":"https://i.ibb.co/K2PDh6f/barun.jpg", "salary":1500},
{"id":4,"name":"Cynthy","email":"ccudbird3@odnoklassniki.ru","gender":"Female", "image":"https://i.ibb.co/dkp2Vy0/ranbir1.jpg", "salary":500},
{"id":5,"name":"Ricky","email":"rkidd4@comsenz.com","gender":"Genderqueer", "image":"https://i.ibb.co/1ZB1BNg/jon.jpg", "salary":2300},
{"id":6,"name":"Bernette","email":"bschild5@businessinsider.com","gender":"Polygender", "image":"https://i.ibb.co/DDrQbFL/khan.jpg", "salary":1340},
{"id":7,"name":"Violante","email":"vhebron6@fema.gov","gender":"Male", "image":"https://i.ibb.co/LvmQjQS/siddrth.jpg", "salary":2000},
{"id":8,"name":"Tamara","email":"tleader7@salon.com","gender":"Female", "image":"https://i.ibb.co/Jkh5db2/khurana.jpg", "salary":4200},
{"id":9,"name":"Lina","email":"lklausewitz8@cnbc.com","gender":"Female", "image":"https://i.ibb.co/nMLxJTz/vagina.jpg", "salary":3426},
{"id":10,"name":"Cello","email":"cmaciaszek9@purevolume.com","gender":"Non-binary", "image":"https://i.ibb.co/mHHXT4Q/akkhay.jpg", "salary":1470},
{"id":11,"name":"Vachel","email":"vhemerijka@craigslist.org","gender":"Female", "image":"https://i.ibb.co/1ZB1BNg/jon.jpg", "salary":234},
{"id":12,"name":"Camey","email":"chillandb@amazonaws.com","gender":"Bigender", "image":"https://i.ibb.co/KXm8bN5/rittik.jpg", "salary":3545},
{"id":13,"name":"Julissa","email":"jshankc@g.co","gender":"Polygender", "image":"https://i.ibb.co/F79NvQ6/hoda.jpg", "salary":6542},
{"id":14,"name":"Petr","email":"phaxbyd@so-net.ne.jp","gender":"Male", "image":"https://i.ibb.co/6sDCgvd/sonu.jpg", "salary":2455},
{"id":15,"name":"Celka","email":"creddine@posterous.com","gender":"Polygender", "image":"https://i.ibb.co/LvmQjQS/siddrth.jpg", "salary":920},
{"id":16,"name":"Bax","email":"bmcandrewf@imageshack.us","gender":"Non-binary", "image":"https://i.ibb.co/DrN5fgn/arjun.jpg", "salary":4523},
{"id":17,"name":"Babs","email":"bkyndredg@chronoengine.com","gender":"Male", "image":"https://i.ibb.co/KXm8bN5/rittik.jpg", "salary":3421},
{"id":18,"name":"Pierette","email":"pbartleeth@elpais.com","gender":"Agender", "image":"https://i.ibb.co/DDrQbFL/khan.jpg", "salary":1233},
{"id":20,"name":"Jolyn","email":"jbinnsj@toplist.cz","gender":"Bigender", "image":"https://i.ibb.co/1ZB1BNg/jon.jpg", "salary":6533}]